{"Step 1": {"Planning": "Pick up the sponge", "Target": ["sponge"], "Expect Scene Graph": [["mug", "ontop", "countertop"], ["teacup", "ontop", "countertop"], ["liquid_soap__bottle", "filled", "liquid_soap"], ["liquid_soap__bottle", "ontop", "countertop"], ["mug", "covered", "low-fat_milk"], ["teacup", "covered", "tea"], ["sink", "insource", "water"], ["agent", "ontop", "floor"]]}, "Step 2": {"Planning": "Pour water into the sink", "Target": ["sink", "water"], "Expect Scene Graph": [["mug", "ontop", "countertop"], ["teacup", "ontop", "countertop"], ["liquid_soap__bottle", "filled", "liquid_soap"], ["liquid_soap__bottle", "ontop", "countertop"], ["mug", "covered", "low-fat_milk"], ["teacup", "covered", "tea"]]}, "Step 3": {"Planning": "Pick up the teacup", "Target": ["teacup"], "Expect Scene Graph": [["mug", "ontop", "countertop"], ["liquid_soap__bottle", "filled", "liquid_soap"], ["liquid_soap__bottle", "ontop", "countertop"], ["mug", "covered", "low-fat_milk"], ["sink", "insource", "water"]]}, "Step 4": {"Planning": "Rinse the teacup in the sink", "Target": ["teacup", "sink"], "Expect Scene Graph": [["mug", "ontop", "countertop"], ["liquid_soap__bottle", "filled", "liquid_soap"], ["liquid_soap__bottle", "ontop", "countertop"], ["mug", "covered", "low-fat_milk"]]}, "Step 5": {"Planning": "Pick up the mug", "Target": ["mug"], "Expect Scene Graph": [["liquid_soap__bottle", "filled", "liquid_soap"], ["liquid_soap__bottle", "ontop", "countertop"], ["sink", "insource", "water"]]}, "Step 6": {"Planning": "Rinse the mug in the sink", "Target": ["mug", "sink"], "Expect Scene Graph": [["liquid_soap__bottle", "filled", "liquid_soap"], ["liquid_soap__bottle", "ontop", "countertop"]]}, "Step 7": {"Planning": "Clean the cups with the sponge and liquid soap", "Target": ["mug", "teacup", "sponge", "liquid_soap"], "Expect Scene Graph": null}}