{"Step 1": {"Planning": "Open the cabinet", "Target": ["cabinet"], "Expect Scene Graph": [["frying_pan", "inside", "cabinet"], ["spatula", "inside", "cabinet"], ["cooking_oil__bottle", "inside", "cabinet"]]}, "Step 2": {"Planning": "Take the frying pan out of the cabinet", "Target": ["cabinet", "frying_pan"], "Expect Scene Graph": [["spatula", "inside", "cabinet"], ["cooking_oil__bottle", "inside", "cabinet"]]}, "Step 3": {"Planning": "Take the spatula out of the cabinet", "Target": ["cabinet", "spatula"], "Expect Scene Graph": [["cooking_oil__bottle", "inside", "cabinet"]]}, "Step 4": {"Planning": "Take the cooking oil bottle out of the cabinet", "Target": ["cabinet", "cooking_oil__bottle"], "Expect Scene Graph": null}, "Step 5": {"Planning": "Open the electric refrigerator", "Target": ["electric_refrigerator"], "Expect Scene Graph": [["tupperware", "inside", "electric_refrigerator"]]}, "Step 6": {"Planning": "Take the tupperware out of the electric refrigerator", "Target": ["electric_refrigerator", "tupperware"], "Expect Scene Graph": null}, "Step 7": {"Planning": "Pour cooking oil into the frying pan", "Target": ["cooking_oil__bottle", "frying_pan"], "Expect Scene Graph": [["cooking_oil__bottle", "inside", "cabinet"], ["frying_pan", "filled", "cooking_oil"]]}}