{"Step 1": {"Planning": "Open the electric refrigerator", "Target": ["electric_refrigerator"], "Expect Scene Graph": [["hamburger", "inside", "electric_refrigerator"], ["tupperware", "inside", "electric_refrigerator"]]}, "Step 2": {"Planning": "Take the hamburger out of the electric refrigerator", "Target": ["electric_refrigerator", "hamburger"], "Expect Scene Graph": [["tupperware", "inside", "electric_refrigerator"]]}, "Step 3": {"Planning": "Take the tupperware out of the electric refrigerator", "Target": ["electric_refrigerator", "tupperware"], "Expect Scene Graph": null}, "Step 4": {"Planning": "Take the platter out of the cabinet", "Target": ["cabinet", "platter"], "Expect Scene Graph": null}, "Step 5": {"Planning": "Put the hamburger on the platter", "Target": ["hamburger", "platter"], "Expect Scene Graph": [["hamburger", "ontop", "platter"]]}, "Step 6": {"Planning": "Open the microwave", "Target": ["microwave"], "Expect Scene Graph": null}, "Step 7": {"Planning": "Put the platter with hamburger in the microwave", "Target": ["platter", "microwave"], "Expect Scene Graph": [["hamburger", "ontop", "platter"]]}}