{"Step 1": {"Planning": "Open the refrigerator", "Target": ["electric_refrigerator"], "Expect Scene Graph": [["turkey", "ontop", "countertop"], ["cookie_sheet", "ontop", "countertop"], ["agent", "ontop", "floor"]]}, "Step 2": {"Planning": "Take the turkey out of the refrigerator", "Target": ["electric_refrigerator", "turkey"], "Expect Scene Graph": [["turkey", "ontop", "countertop"], ["cookie_sheet", "ontop", "countertop"], ["agent", "ontop", "floor"]]}, "Step 3": {"Planning": "Place the turkey on the cookie sheet", "Target": ["turkey", "cookie_sheet"], "Expect Scene Graph": [["turkey", "ontop", "cookie_sheet"], ["cookie_sheet", "ontop", "countertop"], ["agent", "ontop", "floor"]]}, "Step 4": {"Planning": "Store the uncooked turkey", "Target": ["turkey", "countertop"], "Expect Scene Graph": [["turkey", "ontop", "cookie_sheet"], ["cookie_sheet", "ontop", "countertop"], ["agent", "ontop", "floor"]]}}